mtable.py
mtable-0.2.22.dist-info/METADATA
mtable-0.2.22.dist-info/WHEEL
mtable-0.2.22.dist-info/top_level.txt
mtable-0.2.22.dist-info/RECORD
