Metadata-Version: 2.4
Name: mtable
Version: 0.2.22
Summary: format data to reStructedText and Markup Table
Home-page: https://github.com/liuyug/mtable
Author: Yugang LIU
Author-email: liuyug@gmail.com
License: BSD
Requires-Python: >=3
Requires-Dist: chardet
Requires-Dist: wcwidth
Requires-Dist: beautifulsoup4
Dynamic: author
Dynamic: author-email
Dynamic: description
Dynamic: home-page
Dynamic: license
Dynamic: requires-dist
Dynamic: requires-python
Dynamic: summary
